MANIFEST.in
bank_data.xml
bank_view.xml
setup.py
./__init__.py
./__openerp__.py
./bank.py
i18n/ar.po
i18n/es.po
i18n/es_CR.po
i18n/fr.po
i18n/l10n_fr_rib.pot
i18n/nl.po
i18n/pt.po
i18n/pt_BR.po
i18n/sl.po
i18n/tr.po
openerp_l10n_fr_rib.egg-info/PKG-INFO
openerp_l10n_fr_rib.egg-info/SOURCES.txt
openerp_l10n_fr_rib.egg-info/dependency_links.txt
openerp_l10n_fr_rib.egg-info/requires.txt
openerp_l10n_fr_rib.egg-info/top_level.txt